intellireading/client/__about_cli__.py
intellireading/client/__init__.py
intellireading/client/__main__.py
intellireading/client/app.py
intellireading/client/commands.py
intellireading/client/metaguiding.py
intellireading_cli-2.1.0.dist-info/METADATA
intellireading_cli-2.1.0.dist-info/WHEEL
intellireading_cli-2.1.0.dist-info/entry_points.txt
intellireading_cli-2.1.0.dist-info/licenses/LICENSE
intellireading_cli-2.1.0.dist-info/RECORD
