Metadata-Version: 2.4
Name: intellireading-cli
Version: 2.1.0
Summary: Intellireading-cli is a Python library with a set of tools to improve your reading experience
Project-URL: Documentation, https://go.hugobatista.com/gh/intellireading-cli#readme
Project-URL: Issues, https://go.hugobatista.com/gh/intellireading-cli/issues
Project-URL: Source, https://go.hugobatista.com/gh/intellireading-cli
Author: Hugo Batista
License-Expression: GPL-3.0
License-File: LICENSE
Keywords: adhd,calibre,dyslexia,ebook,epub,kepub,kindle,kobo,speed-reading
Classifier: Development Status :: 4 - Beta
Classifier: Intended Audience :: Developers
Classifier: Intended Audience :: Education
Classifier: Intended Audience :: End Users/Desktop
Classifier: Intended Audience :: Information Technology
Classifier: Intended Audience :: Science/Research
Classifier: Intended Audience :: System Administrators
Classifier: License :: OSI Approved :: GNU General Public License v3 (GPLv3)
Classifier: Operating System :: OS Independent
Classifier: Programming Language :: Python
Classifier: Programming Language :: Python :: 3.13
Classifier: Programming Language :: Python :: Implementation :: CPython
Classifier: Programming Language :: Python :: Implementation :: PyPy
Classifier: Topic :: Education :: Computer Aided Instruction (CAI)
Classifier: Topic :: Software Development
Classifier: Topic :: Text Processing :: Markup :: XML
Classifier: Topic :: Utilities
Requires-Python: >=3.13
Requires-Dist: click>=8.1.7
Requires-Dist: lxml>=4.9.2
Requires-Dist: regex>=2024.11.6
